<?xml version="1.0"?>
<!--  File Name: fulldata.xml -->
<WXDATA>
 <PARAM>
  <date>18/05/24</date> 
  <time>11:55</time>
  <stationCity>Jerusalem</stationCity> 
  <stationState>Israel</stationState> 
  <stationElevation>  745 m</stationElevation> 
  <stationDate>18/05/24</stationDate> 
  <stationTime>11:54</stationTime> 
  <utcDate>18/05/24</utcDate>
  <utcTime> 8:55</utcTime>
  <sunriseTime> 5:40</sunriseTime> 
  <sunsetTime>19:32</sunsetTime> 
  <insideTemp>27.2</insideTemp>
  <tempUnit>C</tempUnit> 
  <hiInsideTemp>27.3</hiInsideTemp> 
  <hiInsideTempTime>11:50</hiInsideTempTime> 
  <lowInsideTemp>24.3</lowInsideTemp> 
  <lowInsideTempTime> 6:23</lowInsideTempTime> 
  <hiMonthlyInsideTemp>28.3</hiMonthlyInsideTemp> 
  <lowMonthlyInsideTemp>19.4</lowMonthlyInsideTemp>  
  <hiYearlyInsideTemp>31.1</hiYearlyInsideTemp>  
  <lowYearlyInsideTemp>15.0</lowYearlyInsideTemp>  
  <Temp>30.1</Temp>  
  <hiTemp>30.1</hiTemp> 
  <hiTempTime>11:52</hiTempTime> 
  <lowTemp>19.5</lowTemp>  
  <lowTempTime> 6:06</lowTempTime>
  <hiMonthlyTemp>33.3</hiMonthlyTemp>  
  <lowMonthlyTemp>11.1</lowMonthlyTemp> 
  <hiYearlyTemp>34.4</hiYearlyTemp>  
  <lowYearlyTemp>4.4</lowYearlyTemp>  
  <Temp2>--- </Temp2>
  <hiTemp2>---</hiTemp2> 
  <hiTemp2Time>----</hiTemp2Time>
  <lowTemp2>---</lowTemp2>  
  <lowTemp2Time>----</lowTemp2Time>
  <insideHumidity>33</insideHumidity> 
  <humUnit>% </humUnit> 
  <hiInsideHumidity>43</hiInsideHumidity> 
  <hiInsideHumidityTime> 7:41</hiInsideHumidityTime> 
  <lowInsideHumidity>33</lowInsideHumidity> 
  <lowInsideHumidityTime>11:44</lowInsideHumidityTime> 
  <hiMonthlyInsideHumidity>61</hiMonthlyInsideHumidity> 
  <lowMonthlyInsideHumidity>18</lowMonthlyInsideHumidity> 
  <hiYearlyInsideHumidity>66</hiYearlyInsideHumidity> 
  <lowYearlyInsideHumidity>17</lowYearlyInsideHumidity> 
  <Humidity>27</Humidity> 
  <hiHumidity>54</hiHumidity> 
  <hiHumTime> 6:30</hiHumTime> 
  <lowHumidity>26</lowHumidity> 
  <lowHumTime>11:54</lowHumTime> 
  <hiMonthlyHumidity>95</hiMonthlyHumidity> 
  <lowMonthlyHumidity>11</lowMonthlyHumidity> 
  <hiYearlyHumidity>98</hiYearlyHumidity> 
  <lowYearlyHumidity>11</lowYearlyHumidity> 
  <barometer>1014.5</barometer> 
  <barUnit>mb</barUnit> 
  <barTrend>Steady</barTrend> 
  <hiBarometer>1016.9</hiBarometer>  
  <hiBarometerTime> 0:00</hiBarometerTime> 
  <lowBarometer>1013.9</lowBarometer>  
  <lowBarometerTime> 6:22</lowBarometerTime> 
  <lowMonthlyBarometer>1004.3</lowMonthlyBarometer>  
  <hiMonthlyBarometer>1018.3</hiMonthlyBarometer>  
  <lowYearlyBarometer>1002.0</lowYearlyBarometer>  
  <hiYearlyBarometer>1026.5</hiYearlyBarometer>  
  <windSpeed>6.4</windSpeed> 
  <windUnit>km/hr</windUnit> 
  <wind10Avg>6.4</wind10Avg>
  <wind10Gust>---</wind10Gust>
  <hiWindSpeed>16.1</hiWindSpeed>
  <hiWindSpeedTime> 9:12</hiWindSpeedTime> 
  <hiMonthlyWindSpeed>57.9</hiMonthlyWindSpeed>  
  <hiYearlyWindSpeed>57.9</hiYearlyWindSpeed>  
  <windDir>300</windDir> 
  <windDirection>WNW</windDirection> 
  <windChill>30.1</windChill>  
  <lowWindchill>19.4</lowWindchill>  
  <lowWindchillTime> 5:40</lowWindchillTime> 
  <lowMonthlyWindchill>11.1</lowMonthlyWindchill>  
  <lowYearlyWindchill>0.6</lowYearlyWindchill>  
  <totalRain>326.4</totalRain> 
  <rainUnit>mm</rainUnit> 
  <dailyRain>0.0</dailyRain> 
  <monthlyRain>7.2</monthlyRain> 
  <stormRain>0.0</stormRain> 
  <rainRate>0.0</rainRate> 
  <rateUnit>mm/hr</rateUnit> 
  <hiRainRate>0.0</hiRainRate> 
  <hiRainRateTime>----</hiRainRateTime> 
  <hiRainRateHour>0.0</hiRainRateHour>  
  <hiMonthlyRainRate>49.8</hiMonthlyRainRate>  
  <hiYearlyRainRate>135.6</hiYearlyRainRate>  
  <DewPt>9.0</DewPt>  
  <hiDewpoint>13.3</hiDewpoint>  
  <hiDewpointTime> 7:32</hiDewpointTime> 
  <lowDewpoint>7.8</lowDewpoint>  
  <lowDewpointTime> 2:47</lowDewpointTime> 
  <hiMonthlyDewpoint>17.2</hiMonthlyDewpoint>  
  <lowMonthlyDewpoint>-5.6</lowMonthlyDewpoint>  
  <hiYearlyDewpoint>18.3</hiYearlyDewpoint>  
  <lowYearlyDewpoint>-11.7</lowYearlyDewpoint>  
  <insideDewPt>9.5</insideDewPt>  
  <HeatIndex>28.7</HeatIndex>  
  <hiHeatindex>28.9</hiHeatindex> 
  <hiHeatindexTime>11:34</hiHeatindexTime> 
  <hiMonthlyHeatindex>31.7</hiMonthlyHeatindex> 
  <hiYearlyHeatindex>31.7</hiYearlyHeatindex> 
  <thw>28.7</thw>
  <thsw><!--thsw--></thsw>
  <hiTHSWindex>34.4</hiTHSWindex> 
  <hiTHSWindexTime>11:04</hiTHSWindexTime>
  <hiMonthlyTHSWindex>37.2</hiMonthlyTHSWindex> 
  <hiYearlyTHSWindex>38.3</hiYearlyTHSWindex> 
  <insideHeatIndex>26.2</insideHeatIndex> 
  <emc>5.5</emc>
  <emcUnit>%</emcUnit>
  <airDensity>1.1530</airDensity> 
  <airDensityUnit>kg/cu.m</airDensityUnit>
  <solarRad>951</solarRad>
  <hiSolarRad>953</hiSolarRad>
  <hiSolarRadTime>11:50</hiSolarRadTime>
  <hiMonthlySolarRad>1382</hiMonthlySolarRad>
  <hiYearlySolarRad>1382</hiYearlySolarRad>
  <uv>8.2</uv>
  <hiUV>8.2</hiUV>
  <hiUVTime>11:46</hiUVTime>
  <hiMonthlyUV>9.8</hiMonthlyUV>
  <hiYearlyUV>9.8</hiYearlyUV>
  <dailyET>2.01</dailyET>
  <monthlyET>84.30</monthlyET>
  <yearlyET>451.84</yearlyET>
  </PARAM>
</WXDATA>